switcheroo/__init__.py
switcheroo-2.0.0.dist-info/LICENSE.txt
switcheroo-2.0.0.dist-info/WHEEL
switcheroo-2.0.0.dist-info/METADATA
switcheroo-2.0.0.dist-info/RECORD
