Metadata-Version: 2.1
Name: switcheroo
Version: 2.0.0
Summary: Efficient dispatch-based calling, that might be a switch statement in another language.
Home-page: https://github.com/simplistix/switcheroo
License: MIT
Author: Chris Withers
Author-email: chris@withers.org
Requires-Python: >=3.6,<4.0
Classifier: License :: OSI Approved :: MIT License
Classifier: Programming Language :: Python :: 3
Classifier: Programming Language :: Python :: 3.10
Classifier: Programming Language :: Python :: 3.6
Classifier: Programming Language :: Python :: 3.7
Classifier: Programming Language :: Python :: 3.8
Classifier: Programming Language :: Python :: 3.9
Project-URL: Repository, https://github.com/simplistix/switcheroo
